{
  "cordova-sqlite-storage": {
    "source": {
      "type": "registry",
      "id": "cordova-sqlite-storage"
    },
    "is_top_level": true,
    "variables": {}
  },
  "cordova-plugin-whitelist": {
    "source": {
      "type": "registry",
      "id": "cordova-plugin-whitelist@^1.3.3"
    },
    "is_top_level": true,
    "variables": {}
  },
  "cordova-plugin-statusbar": {
    "source": {
      "type": "registry",
      "id": "cordova-plugin-statusbar@2.4.2"
    },
    "is_top_level": true,
    "variables": {}
  },
  "cordova-plugin-device": {
    "source": {
      "type": "registry",
      "id": "cordova-plugin-device@^2.0.2"
    },
    "is_top_level": true,
    "variables": {}
  },
  "cordova-plugin-splashscreen": {
    "source": {
      "type": "registry",
      "id": "cordova-plugin-splashscreen@^5.0.2"
    },
    "is_top_level": true,
    "variables": {}
  },
  "cordova-plugin-ionic-webview": {
    "source": {
      "type": "registry",
      "id": "cordova-plugin-ionic-webview@^4.1.3"
    },
    "is_top_level": true,
    "variables": {}
  },
  "cordova-plugin-ionic-keyboard": {
    "source": {
      "type": "registry",
      "id": "cordova-plugin-ionic-keyboard@^2.0.5"
    },
    "is_top_level": true,
    "variables": {}
  },
  "cordova-plugin-facebook4": {
    "source": {
      "type": "registry",
      "id": "cordova-plugin-facebook4"
    },
    "is_top_level": true,
    "variables": {
      "APP_ID": "483960429170480",
      "APP_NAME": "androidTest"
    }
  },
  "twitter-connect-plugin": {
    "source": {
      "type": "registry",
      "id": "twitter-connect-plugin"
    },
    "is_top_level": true,
    "variables": {
      "FABRIC_KEY": "zDy6rzmoars9O9sep6Y87XOip",
      "TWITTER_KEY": "zDy6rzmoars9O9sep6Y87XOip",
      "TWITTER_SECRET": "tBSJvHJfiCyWtTE9gbzAzIDibNvdDiXd51SvpBMu9BwJejpIot"
    }
  },
  "cordova-plugin-camera": {
    "source": {
      "type": "registry",
      "id": "cordova-plugin-camera@4.1.0"
    },
    "is_top_level": true,
    "variables": {}
  },
  "onesignal-cordova-plugin": {
    "source": {
      "type": "registry",
      "id": "onesignal-cordova-plugin"
    },
    "is_top_level": true,
    "variables": {}
  },
  "cordova-plugin-uniquedeviceid": {
    "source": {
      "type": "registry",
      "id": "cordova-plugin-uniquedeviceid"
    },
    "is_top_level": true,
    "variables": {}
  },
  "cordova-plugin-network-information": {
    "source": {
      "type": "registry",
      "id": "cordova-plugin-network-information"
    },
    "is_top_level": true,
    "variables": {}
  },
  "cordova-plugin-datepicker": {
    "source": {
      "type": "registry",
      "id": "cordova-plugin-datepicker"
    },
    "is_top_level": true,
    "variables": {}
  },
  "cordova-plugin-geolocation": {
    "source": {
      "type": "registry",
      "id": "cordova-plugin-geolocation@4.0.2"
    },
    "is_top_level": true,
    "variables": {
      "GEOLOCATION_USAGE_DESCRIPTION": "To locate you"
    }
  }
}